MANIFEST.in
README.rst
requirements.txt
setup.py
innercos_python_sdk_v5.egg-info/PKG-INFO
innercos_python_sdk_v5.egg-info/SOURCES.txt
innercos_python_sdk_v5.egg-info/dependency_links.txt
innercos_python_sdk_v5.egg-info/requires.txt
innercos_python_sdk_v5.egg-info/top_level.txt
qcloud_cos/__init__.py
qcloud_cos/cos_auth.py
qcloud_cos/cos_client.py
qcloud_cos/cos_comm.py
qcloud_cos/cos_encryption_client.py
qcloud_cos/cos_exception.py
qcloud_cos/cos_threadpool.py
qcloud_cos/crypto.py
qcloud_cos/demo.py
qcloud_cos/resumable_downloader.py
qcloud_cos/select_event_stream.py
qcloud_cos/streambody.py
qcloud_cos/tce_demo.py
qcloud_cos/version.py
qcloud_cos/xml2dict.py