Metadata-Version: 1.0
Name: innercos-python-sdk-v5
Version: 0.1.0
Summary: innercos-python-sdk-v5
Home-page: https://www.qcloud.com/
Author: maysonshen, tiedu, lewzylu, channingliu
Author-email: dutie123@qq.com
License: MIT
Platform: UNKNOWN
